nonebot_plugin_BR/__init__.py
nonebot_plugin_BR/__main__.py
nonebot_plugin_BR/config.py
nonebot_plugin_BR/game.py
nonebot_plugin_BR/model.py
nonebot_plugin_BR/utils.py
nonebot_plugin_BR/weapon.py
nonebot_plugin_br-0.0.8.dist-info/METADATA
nonebot_plugin_br-0.0.8.dist-info/WHEEL
nonebot_plugin_br-0.0.8.dist-info/entry_points.txt
nonebot_plugin_br-0.0.8.dist-info/licenses/LICENSE
nonebot_plugin_br-0.0.8.dist-info/RECORD
