Metadata-Version: 2.1
Name: nonebot_plugin_BR
Version: 0.0.8
Summary: 基于nonebot2框架的插件，实现交互游戏恶魔轮盘赌
Keywords: game,nonebot2,plugin
Author-Email: Agnes_Digital <Z735803792@163.com>
License: MIT
Classifier: License :: OSI Approved :: MIT License
Classifier: Programming Language :: Python
Classifier: Programming Language :: Python :: 3
Classifier: Programming Language :: Python :: 3.9
Classifier: Programming Language :: Python :: 3.10
Classifier: Programming Language :: Python :: 3.11
Classifier: Programming Language :: Python :: 3.12
Classifier: Operating System :: OS Independent
Project-URL: homepage, https://github.com/Agnes4m/nonebot_plugin_BR
Requires-Python: <4.0,>=3.9
Requires-Dist: nonebot2>=2.2.0
Requires-Dist: nonebot-plugin-uninfo>=0.4.1
Requires-Dist: nonebot_plugin_waiter>=0.8.0
Requires-Dist: nonebot_plugin_session>=0.3.2
